CHANGELOG.txt
LICENCE.txt
MANIFEST.in
README.txt
setup.py
ktuhope/__init__.py
ktuhope.egg-info/PKG-INFO
ktuhope.egg-info/SOURCES.txt
ktuhope.egg-info/dependency_links.txt
ktuhope.egg-info/top_level.txt