Metadata-Version: 2.1
Name: ktuhope
Version: 0.0.4
Summary: Programs on Data Sceince & Machine Learning
Home-page: UNKNOWN
Author: Zhongli
Author-email: 
License: MIT
Keywords: DataScience KTU DSLab
Platform: UNKNOWN
Classifier: Development Status :: 5 - Production/Stable
Classifier: Intended Audience :: Education
Classifier: Operating System :: POSIX :: Linux
Classifier: License :: OSI Approved :: MIT License
Classifier: Programming Language :: Python :: 2.7
Classifier: Programming Language :: Python :: 3.8
License-File: LICENCE.txt
